{
  "_format": "hh-sol-cache-2",
  "files": {
    "C:\\Users\\Aditya singh\\PolyOne\\contracts\\ChainFactory.sol": {
      "lastModificationDate": 1761300103106,
      "contentHash": "c504d27298614994c47e76d91fbc6aa5",
      "sourceName": "contracts/ChainFactory.sol",
      "solcConfig": {
        "version": "0.8.20",
        "settings": {
          "optimizer": {
            "enabled": true,
            "runs": 200
          },
          "evmVersion": "paris",
          "outputSelection": {
            "*": {
              "*": [
                "abi",
                "evm.bytecode",
                "evm.deployedBytecode",
                "evm.methodIdentifiers",
                "metadata"
              ],
              "": [
                "ast"
              ]
            }
          }
        }
      },
      "imports": [],
      "versionPragmas": [
        "^0.8.20"
      ],
      "artifacts": [
        "ChainFactory"
      ]
    },
    "C:\\Users\\Aditya singh\\PolyOne\\contracts\\ChainRegistry.sol": {
      "lastModificationDate": 1761300103107,
      "contentHash": "37b826e0095283ebf2a97a493847ed0c",
      "sourceName": "contracts/ChainRegistry.sol",
      "solcConfig": {
        "version": "0.8.20",
        "settings": {
          "optimizer": {
            "enabled": true,
            "runs": 200
          },
          "evmVersion": "paris",
          "outputSelection": {
            "*": {
              "*": [
                "abi",
                "evm.bytecode",
                "evm.deployedBytecode",
                "evm.methodIdentifiers",
                "metadata"
              ],
              "": [
                "ast"
              ]
            }
          }
        }
      },
      "imports": [],
      "versionPragmas": [
        "^0.8.20"
      ],
      "artifacts": [
        "ChainRegistry"
      ]
    }
  }
}
