{
  "chainId": 73,
  "chainName": "zee",
  "rollupType": "optimistic-rollup",
  "gasToken": "ZEC",
  "validators": 3,
  "chainType": "private",
  "validatorAccess": "public",
  "l1Config": {
    "chainId": 80002,
    "rpcUrl": "https://rpc-amoy.polygon.technology",
    "polygonRollupManagerAddress": "0x..."
  },
  "zkEVMConfig": {
    "globalExitRootAddress": "0x...",
    "dataAvailability": "rollup",
    "blockTime": 2,
    "gasLimit": "0x1312D00"
  },
  "agglayer": {
    "enabled": true,
    "endpoint": "https://agglayer-testnet.polygon.technology",
    "chainId": "7090ab99-a7ef-4881-95c0-73e06a2d55a2"
  }
}